[
    {
        "title": "感冒发烧",
        "infos": [
            {
                "syz": "本品清热解毒，疏风解表。用于上呼吸道感染、急性扁桃体炎、咽喉炎属外感风热、热毒壅盛证，症见发热、咽喉肿痛。",
                "zysx": "1.忌烟﹑酒及辛辣﹑生冷﹑油腻食物。2.不宜在服药期间同时服用滋补性中药。3.风寒感冒者不适用。4.有高血压﹑心脏病﹑肝病﹑糖尿病﹑肾病等慢性病严重者应在医师指导下服用。5.儿童﹑孕妇﹑哺乳期妇女﹑年老体弱及脾虚便溏者应在医师指导下服用。6.扁桃体有化脓或发热体温超过38.5℃的患者应去医院就诊。7.服药3天症状无缓解，应去医院就诊。8.对本品过敏者禁用，过敏体质者慎用。9.本品性状发生改变时禁止使用。10.儿童必须在成人监护下使用。11.请将本品放在儿童不能接触的地方。12.如正在使用其他药品，使用本品前请咨询医师或药师。",
                "id": "55c1e375a2b7b274407c419b",
                "imgUrl":"https://timgsa.baidu.com/timg?image&quality=80&size=b9999_10000&sec=1532977082817&di=556839f4f8519da613dbfe1daa6ac946&imgtype=0&src=http%3A%2F%2Fm.360buyimg.com%2Fn12%2Fjfs%2Ft2743%2F33%2F3643066549%2F334779%2F50572069%2F5795a849N9875e4a6.jpg%2521q70.jpg",
                "zycf": "本品主要成分：大青叶，板蓝根，连翘，拳参。辅料为：糊精，矫味剂(甜菊素)。",
                "ggxh": "每袋装18克。",
                "pzwh": "国药准字Z11021211",
                "zzjb": "上呼吸道感染,急性扁桃体炎,咽喉炎,外感风热,热毒壅盛,发热,咽喉肿痛",
                "zxbz": "",
                "manu": "华润三九(北京)药业有限公司",
                "jj": "对本品成分过敏者禁用。",
                "yxq": "36个月",
                "drugName": "999 感冒退热颗粒",
                "ywxhzy": "如与其他药物同时使用可能会发生药物相互作用，详情请咨询医师或药师。",
                "xz": "本品为棕黄色的颗粒；味甜、微苦。",
                "price": "16.00",
                "yfyl": "开水冲服。一次1~2袋，一日3次。",
                "zc": "密封，在干燥处保存。",
                "postage":"免邮费",
                "stock":35
            },
            {
                "syz": "辛凉解表，清热解毒。本品用于风热感冒之发热，微恶风寒，头身痛，口干而渴，鼻塞涕浊，咽喉红肿疼痛，咳嗽，痰黄粘稠。",
                "zysx": "1.忌烟﹑酒及辛辣﹑生冷﹑油腻食物。 2.不宜在服药期间同时服用滋补性中药。 3.风寒感冒者不适用，其表现为恶寒重，发热轻，无汗，头痛，鼻塞，流清涕，喉痒咳嗽。 4.本品含对乙酰氨基酚﹑马来酸氯苯那敏﹑咖啡因。服用本品期间不得饮酒或含有酒精的饮料; 5.糖尿病患者及有心脏病等慢性病严重者应在医师指导下服用。 6.严格按用法用量服用，儿童﹑年老体弱者应在医师指导下服用。 7.服药2天症状无缓解，应去医院就诊。 8.对本品过敏者禁用，过敏体质者慎用。 9.本品性状发生改变时禁止使用。 10.儿童必须在成人监护下使用。 11.请将本品放在儿童不能接触的地方。 12.如正在使用其他药品，使用本品前请咨询医师或药师。 13.不能同时服用与本品成份相似的其他抗感冒药; 14.肝﹑肾功能不全者慎用;膀胱颈梗阻﹑甲状腺功能亢进﹑青光眼﹑高血压和前列腺肥大者慎用; 15.孕妇及哺乳期妇女慎用; 16.服药期间不得驾驶机﹑车﹑船﹑从事高空作业﹑机械作业及操作精密仪器。",
                "id": "59e962c00ef8f97ff938a5f6",
                "imgUrl": "https://timgsa.baidu.com/timg?image&quality=80&size=b9999_10000&sec=1533014965347&di=c44d23c67991a0fc2e70eeeaf0bebc40&imgtype=0&src=http%3A%2F%2Fc1.yaofangwang.net%2FCommon%2FUpload%2FMedicine%2F590%2F590293%2Fd69e6893-0c1d-4d27-bc20-889d0104fece1275.jpg_syp.jpg",
                "gnzz": "辛凉解表，清热解毒。本品用于风热感冒之发热，微恶风寒，头身痛，口干而渴，鼻塞涕浊，咽喉红肿疼痛，咳嗽，痰黄粘稠。",
                "zycf": "金银花、五指柑、野菊花、三叉苦、南板蓝根、岗梅、对乙酰氨基酚、马来酸氨苯那敏、咖啡因。",
                "ggxh": "14g*9袋",
                "yfyl": "用开水冲服，一次14克，一日3次；二天为一疗程。",
                "blfy": "1.可见困倦，嗜睡，口渴，虚弱感。 2.偶见皮疹，荨麻疹，药热及粒细胞减少。 3.长期大量用药会导致肝肾功能异常。",
                "zc": "密封保存。",
                "tymc": "复方感冒灵颗粒",
                "manu": "华润三九(郴州)制药有限公司",
                "spmc": "复方感冒灵颗粒",
                "jj": "严重肝肾功能不全者禁用。",
                "yxq": "24个月",
                "drugName": "999(复方感冒灵颗粒)",
                "zzjb": "风热感冒,发热,微恶风寒,头身痛,口干而渴,鼻塞涕浊,咽喉红肿,咽喉疼痛,咳嗽,痰黄粘稠",
                "zxbz": "WS3-B-2384-97",
                "ywxhzy": "1.与其他解热镇痛药并用，有增加肾毒性的危险。 2.如与其他药物同时使用可能会发生药物相互作用，详情请咨询医师或药师。",
                "xz": "本品为棕黄色至深棕色的颗粒或块状冲剂；味甜、微苦。",
                "price": "16.00",
                "xgjb": "风热感冒 ,发热 ,微恶风寒 ,头身痛 ,口干而渴 ,鼻塞涕浊 ,咽喉红肿",
                "pzwh": "国药准字Z43020334",
                "postage":"20元包邮",
                "stock":12
            },
            {
                "syz": "辛凉解表，清热解毒。本品用于风热感冒之发热，微恶风寒，头身痛，口干而渴，鼻塞涕浊，咽喉红肿疼痛，咳嗽，痰黄粘稠。",
                "zysx": "1.忌烟﹑酒及辛辣﹑生冷﹑油腻食物。 2.不宜在服药期间同时服用滋补性中药。 3.风寒感冒者不适用，其表现为恶寒重，发热轻，无汗，头痛，鼻塞，流清涕，喉痒咳嗽。 4.本品含对乙酰氨基酚﹑马来酸氯苯那敏﹑咖啡因。服用本品期间不得饮酒或含有酒精的饮料; 5.糖尿病患者及有心脏病等慢性病严重者应在医师指导下服用。 6.严格按用法用量服用，儿童﹑年老体弱者应在医师指导下服用。 7.服药2天症状无缓解，应去医院就诊。 8.对本品过敏者禁用，过敏体质者慎用。 9.本品性状发生改变时禁止使用。 10.儿童必须在成人监护下使用。 11.请将本品放在儿童不能接触的地方。 12.如正在使用其他药品，使用本品前请咨询医师或药师。 13.不能同时服用与本品成份相似的其他抗感冒药; 14.肝﹑肾功能不全者慎用;膀胱颈梗阻﹑甲状腺功能亢进﹑青光眼﹑高血压和前列腺肥大者慎用; 15.孕妇及哺乳期妇女慎用; 16.服药期间不得驾驶机﹑车﹑船﹑从事高空作业﹑机械作业及操作精密仪器。",
                "id": "5af80cc9ca3e848a6b0a2891",
                "imgUrl": "https://timgsa.baidu.com/timg?image&quality=80&size=b9999_10000&sec=1533014965349&di=5977102812529324f7c9bd026d514813&imgtype=0&src=http%3A%2F%2Fpic4.360img.cn%2Fimgs%2F1%2Fitem%2F20171117%2F16184032829812.jpg",
                "gnzz": "辛凉解表，清热解毒。本品用于风热感冒之发热，微恶风寒，头身痛，口干而渴，鼻塞涕浊，咽喉红肿疼痛，咳嗽，痰黄粘稠。",
                "zycf": "金银花、五指柑、野菊花、三叉苦、南板蓝根、岗梅、对乙酰氨基酚、马来酸氨苯那敏、咖啡因。",
                "ggxh": "14g*9袋",
                "yfyl": "用开水冲服，一次14克，一日3次；二天为一疗程。",
                "blfy": "1.可见困倦，嗜睡，口渴，虚弱感。 2.偶见皮疹，荨麻疹，药热及粒细胞减少。 3.长期大量用药会导致肝肾功能异常。",
                "zc": "密封保存。",
                "tymc": "复方感冒灵颗粒",
                "manu": "华润三九(郴州)制药有限公司",
                "spmc": "复方感冒灵颗粒",
                "jj": "严重肝肾功能不全者禁用。",
                "yxq": "24个月",
                "drugName": "999(复方感冒灵颗粒)",
                "zzjb": "风热感冒,发热,微恶风寒,头身痛,口干而渴,鼻塞涕浊,咽喉红肿,咽喉疼痛,咳嗽,痰黄粘稠",
                "zxbz": "WS3-B-2384-97",
                "ywxhzy": "1.与其他解热镇痛药并用，有增加肾毒性的危险。 2.如与其他药物同时使用可能会发生药物相互作用，详情请咨询医师或药师。",
                "xz": "本品为棕黄色至深棕色的颗粒或块状冲剂；味甜、微苦。",
                "price": "15.00",
                "xgjb": "风热感冒 ,发热 ,微恶风寒 ,头身痛 ,口干而渴 ,鼻塞涕浊 ,咽喉红肿",
                "pzwh": "国药准字Z43020334",
                "postage":"免邮费",
                "stock":8
            },
            {
                "syz": "本品清热解毒，疏风解表。用于上呼吸道感染、急性扁桃体炎、咽喉炎属外感风热、热毒壅盛证，症见发热、咽喉肿痛。",
                "zysx": "1.忌烟﹑酒及辛辣﹑生冷﹑油腻食物。|2.不宜在服药期间同时服用滋补性中药。|3.风寒感冒者不适用。|4.有高血压﹑心脏病﹑肝病﹑糖尿病﹑肾病等慢性病严重者应在医师指导下服用。|5.儿童﹑孕妇﹑哺乳期妇女﹑年老体弱及脾虚便溏者应在医师指导下服用。|6.扁桃体有化脓或发热体温超过38.5℃的患者应去医院就诊。|7.服药3天症状无缓解，应去医院就诊。|8.对本品过敏者禁用，过敏体质者慎用。|9.本品性状发生改变时禁止使用。|10.儿童必须在成人监护下使用。|11.请将本品放在儿童不能接触的地方。|12.如正在使用其他药品，使用本品前请咨询医师或药师。",
                "id": "59e962c20ef8f97ff938a615",
                "imgUrl": "http://app2.showapi.com/img/drug2/201805/1526205639033.jpg",
                "gnzz": "本品清热解毒，疏风解表。用于上呼吸道感染、急性扁桃体炎、咽喉炎属外感风热、热毒壅盛证，症见发热、咽喉肿痛。",
                "zycf": "本品主要成分：大青叶，板蓝根，连翘，拳参。辅料为：糊精，矫味剂(甜菊素)。",
                "ggxh": "每袋装18克",
                "yfyl": "开水冲服。一次1~2袋，一日3次。",
                "blfy": "尚不明确。",
                "zc": "密封，在干燥处保存。",
                "tymc": "感冒退热颗粒",
                "manu": "华润三九(北京)药业有限公司",
                "spmc": "",
                "jj": "对本品成分过敏者禁用。",
                "yxq": "36个月",
                "drugName": "999(感冒退热颗粒)",
                "zzjb": "上呼吸道感染,急性扁桃体炎,咽喉炎,外感风热,热毒壅盛,发热,咽喉肿痛",
                "zxbz": "",
                "ywxhzy": "如与其他药物同时使用可能会发生药物相互作用，详情请咨询医师或药师。",
                "xz": "本品为棕黄色的颗粒；味甜、微苦。",
                "price": "16.00",
                "xgjb": "上呼吸道感染 ,急性扁桃体炎 ,咽喉炎 ,外感风热 ,热毒壅盛 ,发热 ,咽喉肿痛",
                "pzwh": "国药准字Z11021211",
                "postage":"免邮费",
                "stock":22
            },
            {
                "syz": "疏散风热，清热止咳。用于小儿感冒发烧，汗出不爽，鼻塞流涕，咳嗽咽痛。",
                "zysx": "1.忌辛辣、生冷、油腻食物。|2.不宜在服药期间同时服用滋补性中药。|3.婴儿应在医师指导下服用。|4.风寒感冒者不适用。|5.糖尿病患儿、脾虚易腹泻者应在医师指导下服用。|6.发热体温超过38.5℃的患者，应去医院就诊。|7.服药3天症状无缓解，应去医院就诊。|8.对本品过敏者禁用，过敏体质者慎用。|9.本品性状发生改变时禁止使用。|10.儿童必须在成人监护下使用。",
                "id": "59e962c40ef8f97ff938a62e",
                "imgUrl": "http://app2.showapi.com/img/drug2/201806/1529586457507.jpg",
                "gnzz": "疏散风热，清热止咳。用于小儿感冒发烧，汗出不爽，鼻塞流涕，咳嗽咽痛。",
                "zycf": "广藿香，菊花，连翘，大青叶，板蓝根，地黄，地骨皮等。",
                "ggxh": "每袋装25g",
                "yfyl": "用开水冲服。|1.一岁以内一次半袋。|2.一岁至三岁一次半袋-1袋。|3.四岁至七岁一次1-1.5袋。|4.八岁至十二岁一次袋一日2次。",
                "blfy": "尚不明确。",
                "zc": "密封，置阴凉处。",
                "tymc": "小儿感冒宁颗粒",
                "manu": "三九医药股份有限公司",
                "spmc": "",
                "jj": "对本品过敏者禁用，过敏体质者慎用。",
                "yxq": "24个月",
                "drugName": "999小儿感冒宁颗粒",
                "zzjb": "小儿感冒,小儿发烧,汗出不爽,鼻塞,流涕,咳嗽,咽痛",
                "zxbz": "",
                "ywxhzy": "如与其他药物同时使用可能会发生药物相互作用，详情请咨询医师或药师。",
                "xz": "",
                "price": "12.00",
                "xgjb": "小儿感冒 ,小儿发烧 ,汗出不爽 ,鼻塞 ,流涕 ,咳嗽 ,咽痛",
                "pzwh": "国药准字Z20100067",
                "postage":"20元包邮",
                "stock":36
            },
            {
                "syz": "适用于缓解下列症状：牙痛、头痛、原发性痛经，肩痛、肌痛及运动后损伤性疼痛；劳损、腱鞘炎、滑囊炎引起的疼痛；骨关节炎引起的关节肿痛；以及普通感冒或流行性感冒引起的发热。",
                "zysx": "1.本品为对症治疗药，不宜长期或大量使用，用于止痛不得超过5天，用于解热不得超过3天，如症状不缓解，请咨询医师或药师。 2.必须整粒吞服，不得打开或溶解后服用。 3.不能同时服用其他含有解热镇痛药的药品（如某些复方抗感冒药）。 4.服用本品期间不得饮酒或含有酒精的饮料。 5.有下列情况患者慎用：60岁以上、支气管哮喘、肝肾功能不全、凝血机制或血小板功能障碍（如血友病）。 6.下列情况患者应在医师指导下使用：有消化性溃疡史、胃肠道出血、心功能不全、高血压。 7.如服用过量或出现严重不良反应，应立即就医。 8.对本品过敏者禁用，过敏体质者慎用。 9.本品性状发生改变时禁止使用。 10.请将本品放在儿童不能接触的地方。 11.如正在使用其他药品，使用本品前请咨询医师或药师。",
                "id": "59d9cc640ef8f97ff938a474",
                "imgUrl": "http://app2.showapi.com/img/drug2/201710/1507445859454.png",
                "gnzz": "适用于缓解下列症状：牙痛、头痛、原发性痛经，肩痛、肌痛及运动后损伤性疼痛；劳损、腱鞘炎、滑囊炎引起的疼痛；骨关节炎引...",
                "zycf": "本品主要成分布洛芬。",
                "ggxh": "0.3g*30粒",
                "yfyl": "口服。成人，一次1粒，一日2次（早晚各一次）。",
                "blfy": "1.少数病人可出现恶心、呕吐、胃烧灼感或轻度消化不良、胃肠道溃疡及出血、转氨酶升高、头痛、头晕、耳鸣、视力模糊、精神紧张、嗜睡、下肢水肿或体重骤增。 2.罕见皮疹、过敏性肾炎、膀胱炎、肾病综合征、肾乳头坏死或肾功能衰竭、支气管痉挛。",
                "zc": "密封。",
                "tymc": "布洛芬缓释胶囊",
                "manu": "北京红林制药有限公司",
                "spmc": "",
                "jj": "1.对其他非甾体抗炎药过敏者禁用。 2.孕妇及哺乳期妇女禁用。 3.对阿司匹林过敏的哮喘患者禁用。",
                "yxq": "24个月",
                "drugName": "久保芬(布洛芬缓释胶囊)",
                "zzjb": "头痛,偏头痛,牙痛,痛经,类风湿性关节炎,滑囊炎,痛经,腱鞘炎,骨关节炎,风湿性关节炎,偏头痛,类风湿关节炎,创伤,头痛,痛风",
                "zxbz": "《中国药典》2005年版二部",
                "ywxhzy": "1.本品与其他解热、镇痛、抗炎药物同用时可增加胃肠道不良反应，并可能导致溃疡。 2.本品与肝素、双香豆素等抗凝药同用时，可导致凝血酶原时间延长，增加出血倾向。 3.本品与地高辛、甲氨蝶呤、口服降血糖药物同用时，能使这些药物的血药浓度增高，不宜同用。 4.本品与呋塞米（呋喃苯胺酸）同用时，后者的排钠和降压作用减弱；与抗高血压药同用时，也降低后者的降压效果。 5.如与其他药物同时使用可能会发生药物相互作用，详情请咨询医师或药师。",
                "xz": "本品为缓释胶囊，内容物为白色球形小丸。",
                "price": "18.90",
                "xgjb": "头痛 ,偏头痛 ,牙痛 ,痛经 ,类风湿性关节炎 ,滑囊炎 ,痛经",
                "pzwh": "国药准字H20074172",
                "postage":"20元包邮",
                "stock":8
            }
        ]
    },
    {
        "title":"肠胃用药",
        "infos":[
            {
                "syz": "清热燥湿，行气活血，柔肝止痛，消炎止痛，理气健脾。用于上腹隐痛，饱胀，反酸，恶心，呕吐，纳减，心口嘈杂。",
                "zysx": "1.忌食辛辣刺激性食物。 |2.忌情绪激动或生闷气。 |3.浅表性、糜烂性、萎缩性等慢性胃炎应在医师指导下服用。 |4.孕妇慎用。 |5.慢性胃炎患者服药二周症状无改善，应立即停药并去医院就诊。 |6.按照用法用量服用，小儿、年老体弱者应在医师指导下服用。 |7.对本品过敏者禁用，过敏体质者慎用。 |8.本品性状发生改变时禁止使用。 |9.儿童必须在成人监护下使用。 |10.请将本品放在儿童不能接触的地方。 |11.如正在使用其他药品，使用本品前请咨询医师或药师。",
                "id": "59e962c20ef8f97ff938a60f",
                "imgUrl": "http://app2.showapi.com/img/drug2/201806/1529586450720.png",
                "gnzz": "清热燥湿，行气活血，柔肝止痛，消炎止痛，理气健脾。用于上腹隐痛，饱胀，反酸，恶心，呕吐，纳减，心口嘈杂。",
                "zycf": "三叉苦、黄芩、九里香、两面针、木香、茯苓、白芍、地黄。辅料为叶绿素铜钠、滑石粉、羧甲基纤维素钠。",
                "ggxh": "0.5g*24粒",
                "yfyl": "口服，一次2～4粒，一日2次。",
                "blfy": "尚不明确。",
                "zc": "密封。",
                "tymc": "三九胃泰胶囊",
                "manu": "华润三九医药股份有限公司",
                "spmc": "三九胃泰胶囊",
                "jj": "尚不明确。",
                "yxq": "24个月",
                "drugName": "999三九胃泰胶囊",
                "zzjb": "清热燥湿,行气活血,柔肝止痛,消炎止痛,理气健脾",
                "zxbz": "《中国药典》20lO年版一部",
                "ywxhzy": "如与其他药物同时使用可能会发生药物相互作用，详情请咨询医师或药师。",
                "xz": "本品为胶囊剂。内容物为白色或类白色结晶性粉末，无臭，无味。",
                "price": "20.00",
                "xgjb": "清热燥湿 ,行气活血 ,柔肝止痛 ,消炎止痛 ,理气健脾",
                "pzwh": "国药准字Z44020704",
                "postage":"免邮费",
                "stock":12
            },
            {
                "syz": "增进食欲，纠正偏食厌食，促进消化吸收。",
                "zysx": "无",
                "id": "5b2ba31aca3e848a6b0a28df",
                "imgUrl": "http://app2.showapi.com/img/drug2/201806/1529586457453.jpg",
                "gnzz": "增进食欲，纠正偏食厌食，促进消化吸收。",
                "zycf": "淮山、茯苓、山楂、大枣、扁豆、西番莲汁等。",
                "ggxh": "10ml*10支 10ml*10支",
                "yfyl": "每次10ml，每日2-3次，饭前30分钟服用为佳。|将吸管从封口中心圆点直接插入即可饮用。",
                "blfy": "-",
                "zc": "阴凉闭光处",
                "tymc": "甜酸型健脾养胃液",
                "manu": "华润三九医药股份有限公司",
                "spmc": "三九童泰",
                "jj": "无",
                "yxq": "无",
                "drugName": "三九童泰(甜酸型健脾养胃液)",
                "zzjb": "增进食欲,偏食,厌食,促进消化",
                "zxbz": "",
                "ywxhzy": "适合于2-14岁少年儿童饮用，尤其适用于脾胃虚弱、食欲不佳、消化不良的儿童。",
                "xz": "",
                "price": "16.50",
                "xgjb": "增进食欲 ,偏食 ,厌食 ,促进消化",
                "pzwh": "卫食健字(96)第022号",
                "postage":"20元包邮",
                "stock":15
            },
            {
                "syz": "益气固本，滋阴养胃，调理中焦，行气消导。用于气阴两虚引起的胃脘灼热胀痛，手足心热，口干，口苦，纳差等症，及慢性萎缩性胃炎，慢性胃炎有上述证候者。",
                "zysx": "1．孕妇慎用。 2．湿热胃痛证及重度胃痛应在医师指导下服用。 3．儿童及年老体虚患者应在医师指导下服用。 4．服本药三天症状未改善，应停止服用，并在医院就诊。 5．对本品过敏者禁用，过敏体质者慎用。 6．本品性状发生改变时禁止使用。 7．儿童必须在成人监护下使用。 8．请将本品放在儿童不能接触的地方。 9．如正在使用其他药品。使用本品前请咨询医师或药师。",
                "id": "59e962c00ef8f97ff938a5f2",
                "imgUrl": "http://app2.showapi.com/img/drug2/201805/1526205640936.png",
                "gnzz": "益气固本，滋阴养胃，调理中焦，行气消导。用于气阴两虚引起的胃脘灼热胀痛，手足心热，口干，口苦，纳差等症，及慢性萎缩性...",
                "zycf": "主要成份是白术﹑北沙参﹑陈皮﹑党参﹑干姜﹑黄精﹑山药﹑山楂﹑菟丝子﹑乌梅﹑玄参。",
                "ggxh": "10g*6袋",
                "yfyl": "开水冲服，一次1-2袋，一日2次。",
                "blfy": "尚不明确。",
                "zc": "密封。",
                "tymc": "养胃舒颗粒",
                "manu": "合肥华润神鹿药业有限公司",
                "spmc": "养胃舒颗粒",
                "jj": "对本品过敏者禁用，过敏体质者慎用。",
                "yxq": "24个月",
                "drugName": "999养胃舒颗粒",
                "zzjb": "胃炎,慢性胃炎",
                "zxbz": "",
                "ywxhzy": "如与其他药物同时使用可能会发生药物相互作用，详情请咨询医师或药师。",
                "xz": "本品为浅棕黄色的颗粒；味酸、甜。",
                "price": "22.20",
                "xgjb": "胃炎 ,慢性胃炎",
                "pzwh": "国药准字Z34020289",
                "postage":"免邮费",
                "stock":20
            },
            {
                "syz": "用于普通感冒或流行性感冒引起的发热，也用于缓解轻至中度疼痛如头痛、关节痛、偏头痛、牙痛、肌肉痛、神经痛、痛经。",
                "zysx": "1. 本品为对症治疗药，用于解热连续使用不超过3天，用于止痛不超过5天，症状未缓解请咨询医师或药师。|2. 不能同时服用其他含有解热镇痛药的药品（如某些复方抗感冒药）。|3. 必须整片吞服，不得碾碎或溶解后服用。|4. 年老体弱患者应在医师指导下使用。|5. 服用本品期间不得饮酒或含有酒精的饮料。|6. 痛风、肝肾功能减退、心功能不全、鼻出血、月经过多以及有溶血性贫血史的患者慎用。|7. 发热伴脱水的患儿慎用。|8. 如服用过量或出现严重不良反应，应立即就医。|9. 对本品过敏者禁用，过敏体质者慎用。|10. 本品性状发生改变时禁止使用。|11. 请将本品放在儿童不能接触的地方。|12. 儿童必须在成人监护下使用。|13. 如正在使用其他药品，使用本品前请咨询医师或药师。",
                "id": "5a41bb689cdf9770590477de",
                "imgUrl": "http://app2.showapi.com/img/drug2/201712/1514257316814.jpg",
                "gnzz": "用于普通感冒或流行性感冒引起的发热，也用于缓解轻至中度疼痛如头痛、关节痛、偏头痛、牙痛、肌肉痛、神经痛、痛经。",
                "zycf": "本品主要成份:阿司匹林。",
                "ggxh": "100mg",
                "yfyl": "用法:口服。肠溶片应饭前用适量水送服。|1.降低急性心肌梗死疑似患者的发病风险:建议首次剂量300mg，嚼碎后服用以快速吸收。以后每天100-200mg。|2.预防心肌梗死复发:每天100-300mg。|3.中风的二级预防:每天100-200mg。|4.降低短暂性脑缺血发作(TIA)及其继发脑卒中的风险:每天100-200mg。|5.降低稳定性和不稳定性心绞痛患者的发病风险:每天100-300mg。|6.动脉外科手术或介入手术后，如经皮冠脉腔内成形术(PTCA)，冠状动脉旁路术(CABG)，颈动脉内膜剥离术，动静脉分流术:每天100-300mg。|7.预防大手术后深静脉血栓和肺栓塞:每天100-200mg。|8.降低心血管危险因素者(冠心病家族史﹑糖尿病﹑血脂异常﹑高血压﹑肥胖﹑抽烟史﹑年龄大于50岁者)心肌梗死发作的风险:每天100mg。",
                "blfy": "1.较常见的有恶心、呕吐、上腹部不适或疼痛等胃肠道反应。|2.较少见或罕见的有|（1）胃肠道出血或溃疡，表现为血性或柏油样便，胃部剧痛或呕吐血性或咖啡样物，多见于大剂量服药患者。|（2）支气管痉挛性过敏反应，表现为呼吸困难或哮喘。|（3）皮肤过敏反应，表现为皮疹、荨麻疹、皮肤瘙痒等。|（4）血尿、眩晕和肝脏损害。",
                "zc": "避光，密封。",
                "tymc": "阿司匹林肠溶片",
                "manu": "拜耳医药保健有限公司",
                "spmc": "拜阿司匹灵",
                "jj": "1.孕妇、哺乳期妇女禁用。|2.哮喘、鼻息肉综合征、对阿司匹林和其他解热镇痛药过敏者禁用。|3.血友病或血小板减少症、溃疡病活动期患者禁用。",
                "yxq": "60个月",
                "drugName": "拜阿司匹灵(阿司匹林肠溶片)",
                "zzjb": "急性心肌梗死,心肌梗死,中风,短暂性脑缺血发作,继发脑卒中,不稳定性心绞痛,稳定性心绞痛,心绞痛,经皮冠脉腔内成形术,PTCA,冠状动脉旁路术,CABG,颈动脉内膜剥离术,动静脉分流术,小儿风湿热",
                "zxbz": "",
                "ywxhzy": "1.本品不宜与抗凝血药（如双香豆素、肝素）及溶栓药（链激酶）同用。|2.抗酸药如碳酸氢钠等可增加本品自尿中的排泄，使血药浓度下降，不宜同用。|3.本品与糖皮质激素（如地塞米松等）同用，可增加胃肠道不良反应。|4.本品可加强口服降糖药及甲氨蝶呤的作用，不应同用。|5.如与其他药物同时使用可能会发生药物相互作用，详情请咨询医师或药师。",
                "xz": "片剂",
                "price": "13.90",
                "xgjb": "急性心肌梗死 ,心肌梗死 ,中风 ,短暂性脑缺血发作 ,继发脑卒中 ,不稳定性心绞痛 ,稳定性心绞痛",
                "pzwh": "注册证号H20120236",
                "postage":"20元包邮",
                "stock":3
            },
            {
                "syz": "补中益气，健脾和胃，涩肠止泻。用于脾虚泄泻症，临床表现为腹泻腹痛、腹胀、肠鸣。",
                "zysx": "1.服药期间忌食生冷、辛辣油腻之物。 2.感冒发热者慎用。 3.服药三天症状未改善，或症状加重，或出现新的症状者，应立即停药并去医院就诊。 4.有慢性结肠炎、溃疡性结肠炎便脓血等慢性病史者，患泄泻后应在医师指导下使用。 5.小儿用法用量，请咨询医师或药师。 6.对本品过敏者禁用，过敏体质者慎用。 7.本品性状发生改变时禁止使用。 8.儿童必须在成人监护下使用。 9.请将本品放在儿童不能接触的地方。 10.如正在使用其他药品，使用本品前请咨询医师或药师。",
                "id": "59e962c10ef8f97ff938a602",
                "imgUrl": "http://app2.showapi.com/img/drug2/201710/1508467398170.jpg",
                "gnzz": "补中益气，健脾和胃，涩肠止泻。用于脾虚泄泻症，临床表现为腹泻腹痛、腹胀、肠鸣。",
                "zycf": "黄芪、党参(米炒)、砂仁、白芍、白术(土炒)、肉桂、延胡索(制)、干姜(炮)、防风、木香、补骨脂(盐制)、赤石脂(煅)等15味。",
                "ggxh": "90g",
                "yfyl": "口服，一次6克，一日3次。",
                "blfy": "尚不明确。",
                "zc": "密闭，防潮。",
                "tymc": "补脾益肠丸",
                "manu": "华润三九医药股份有限公司",
                "spmc": "补脾益肠丸",
                "jj": "孕妇禁用；泄泻时腹部热胀痛者忌服。",
                "yxq": "24个月",
                "drugName": "999补脾益肠丸",
                "zzjb": "脾虚泄泻症,腹泻",
                "zxbz": "部标十八册",
                "ywxhzy": "如与其他药物同时使用可能会发生药物相互作用，详情请咨询医师或药师。",
                "xz": "本品为胃肠分溶型水蜜丸；断层可见两层，外层黑褐色，内层红棕色；气香、味甘辛、微苦。",
                "price": "12.00",
                "xgjb": "脾虚泄泻症 ,腹泻",
                "pzwh": "国药准字Z44023376",
                "postage":"免邮费",
                "stock":5
            }
        ]
    },
    {
        "title":"皮肤用药",
        "infos":[
            {
                "syz": "用于轻度烧伤、创伤及蚊虫叮咬引起的各种皮肤感染。",
                "zysx": "1.本品不宜大面积长期使用。2.避免接触眼睛和其他黏膜（如口、鼻等）。3.用药部位如有烧灼感、红肿等情况应停药，并将局部药物洗净，必要时向医师咨询。4.对本品过敏者禁用，过敏体质者慎用。5.本品性状发生改变时禁止使用。6.请将本品放在儿童不能接触的地方。7.儿童必须在成人监护下使用。8.如正在使用其他药品，使用本品前请咨询医师或药师。",
                "id": "55c1e2e9a2b7b274407c3ed8",
                "imgUrl":"https://timgsa.baidu.com/timg?image&quality=80&size=b9999_10000&sec=1532976956984&di=71e855ba46f0e9a636a273de2a0af976&imgtype=0&src=http%3A%2F%2Fc1.yaofangwang.net%2FCommon%2FUpload%2FMedicine%2F190%2F190977%2F1c489abd-c8d7-45a9-b83c-5d2cfebb0ef39379.jpg_syp.jpg",
                "zycf": "本品为复方制剂，每克含林可霉素5毫克，利多卡因4毫克。辅料为：",
                "ggxh": "10克:盐酸林可霉素0.05克(以林可霉素计)与盐酸利多卡因0.04克",
                "pzwh": "国药准字H20058396",
                "zzjb": "烧伤,创伤,眼球挫伤,酸烧伤",
                "zxbz": "",
                "manu": "重庆华邦制药有限公司",
                "jj": "1个月以内婴儿禁用。",
                "yxq": "36个月",
                "drugName": "林可霉素利多卡因凝胶",
                "ywxhzy": "如与其他药物同时使用可能会发生药物相互作用，详情请咨询医师或药师。",
                "xz": "本品为绿色透明的水性凝胶",
                "price": "4.90",
                "yfyl": "外用。涂搽患处，一日2～3次。",
                "zc": "遮光，密闭保存",
                "blfy": "偶见皮肤刺激如烧灼感，或过敏反应如皮疹、瘙痒等。",
                "type": "外科疾病",
                "postage":"免邮费",
                "stock":9
            },
            {
                "syz": "用于轻度烧伤、创伤及蚊虫叮咬引起的各种皮肤感染。",
                "zysx": "1.本品不宜大面积长期使用。2.避免接触眼睛和其他黏膜（如口、鼻等）。3.用药部位如有烧灼感、红肿等情况应停药，并将局部药物洗净，必要时向医师咨询。4.对本品过敏者禁用，过敏体质者慎用。5.本品性状发生改变时禁止使用。6.请将本品放在儿童不能接触的地方。7.儿童必须在成人监护下使用。8.如正在使用其他药品，使用本品前请咨询医师或药师。",
                "id": "55c1e2eca2b7b274407c3ee1",
                "imgUrl":"https://timgsa.baidu.com/timg?image&quality=80&size=b9999_10000&sec=1532976750101&di=709fa85a0a7d2a4eb193d6a28dde127d&imgtype=0&src=http%3A%2F%2Fimg.rmttjkw.com%2Fproduct%2F2016%2F03%2F04%2F201603041027562.jpg",
                "zycf": "本品为复方制剂，每克含林可霉素5毫克，利多卡因4毫克。辅料为：",
                "ggxh": "10g",
                "pzwh": "国药准字H42022314",
                "zzjb": "烧伤,创伤,眼球挫伤,酸烧伤",
                "zxbz": "",
                "manu": "湖北康正药业有限公司",
                "jj": "1个月以内婴儿禁用。",
                "yxq": "24个月",
                "drugName": "林可霉素利多卡因凝胶",
                "ywxhzy": "如与其他药物同时使用可能会发生药物相互作用，详情请咨询医师或药师。",
                "xz": "",
                "price": "1.60",
                "yfyl": "外用。搽于患处，一日2～3次。",
                "zc": "遮光，密闭保存",
                "blfy": "偶见皮肤刺激如烧灼感，或过敏反应如皮疹、瘙痒等。",
                "type": "外科疾病",
                "postage":"20元包邮",
                "stock":10
            },
            {
                "syz": "杀菌,止痒。本品用于脚癣﹑手癣﹑指（趾）甲癣。",
                "zysx": "1.外用药切忌入口，严防触及眼、口、鼻等粘膜之处，皮肤破损处慎用。2.本品对皮肤具有渗透作用并能溶解皮肤角质，部分患者使用后有皮肤表皮脱落现象，不需其他治疗，一周后可停止脱落。本品不适用于糜烂渗出型脚湿气。3.如患肢出现红肿热痛；色如涂丹，应停用本品，去医院就诊。4.按用法用量使用后未见改善症状者，应去医院就诊。5.患处不宜热水洗烫。6.对本品过敏者禁用，过敏体质者慎用。7.儿童必须在成人的监护下使用。8.本品性状发生改变时禁止使用。9.请将本品放在儿童不能接触的地方。10.如正在使用其他药品，使用本品前请咨询医师或药师。",
                "id": "55c1e5a4a2b7b274407c4d87",
                "imgUrl":"https://timgsa.baidu.com/timg?image&quality=80&size=b9999_10000&sec=1532976665334&di=1b56fa414afff837c0462d4c5c7f9968&imgtype=0&src=http%3A%2F%2Fimg.360kad.com%2FUploadFiles%2FDrugs%2F2014%2F3%2F2014328145845.jpg",
                "zycf": "复方珊瑚姜酊、水杨酸、甘油、醋酸等。",
                "ggxh": "250ml",
                "pzwh": "国药准字Z52020136",
                "zzjb": "真菌性皮肤病,体癣,甲癣,足癣,手癣",
                "zxbz": "",
                "manu": "贵州金桥药业有限公司",
                "jj": "对本品成分过敏者禁用。",
                "yxq": "24个月",
                "drugName": "速宁达 珊瑚癣净",
                "ywxhzy": "如与其他药物同时使用可能会发生药物相互作用,详情请咨询医师或药师。",
                "xz": "为草绿色至蓝绿色的澄清液体；具茉莉香气，久闻有刺鼻感。",
                "price": "20.80",
                "yfyl": "外用，取本品250毫升，置脚盆中，加入等量温水稀释后，将患脚浸泡30分钟即可。如未痊愈，可于20天后再浸泡一次。",
                "zc": "密封，置阴凉干燥处。",
                "blfy": "偶见轻型接触性皮炎，少数浸泡后出现干燥、粗糙、干裂与大量脱屑现象。",
                "type": "皮肤疾病",
                "postage":"免邮费",
                "stock":22
            },
            {
                "syz": "清血解毒，消肿止痒。本品用于经络不和，湿热血燥引起的风疹，湿疹，皮肤刺痒，雀斑粉刺，面赤鼻，疮疡肿毒，脚气疥癣，头目眩晕，大便燥结。",
                "zysx": "1.感冒期间停服。2.风寒证或肺脾气虚证荨麻疹不宜使用。3.月经期或哺乳期慎服。4.忌食鱼﹑虾﹑油腻食品；忌酒﹑辛辣刺激食物。5.体弱﹑慢性腹泻者慎用。6.过敏体质者慎用。7.如有油脂性成分渗达表面导致外观颜色变化，不影响服用。",
                "id": "55c1eabba2b7b274407c6b7b",
                "imgUrl":"https://timgsa.baidu.com/timg?image&quality=80&size=b9999_10000&sec=1532976597879&di=a505f4d5d3f09f6139839a3b3d201151&imgtype=0&src=http%3A%2F%2Fi13.wkimg.com%2Fyaoimg%2Fthumbs240%2F2012%2F01%2F05%2F1325758945_1.jpg",
                "zycf": "茜草﹑桃仁﹑荆芥穗（炭）﹑蛇蜕（酒炙）﹑赤芍﹑当归﹑白茅根﹑地肤子﹑苍耳子（炒）﹑地黄﹑连翘﹑金银花﹑苦地丁﹑土茯苓﹑黄柏﹑皂角刺﹑桔梗﹑益母草﹑苦杏仁（去皮炒）﹑防风﹑赤茯苓﹑白芍﹑蝉蜕﹑牛蒡子（炒）﹑牡丹皮﹑白鲜皮﹑熟地黄﹑大黄（酒炒）﹑忍冬藤﹑紫草﹑土贝母﹑川芎（酒炙）﹑甘草﹑白芷﹑天葵子﹑紫荆皮﹑鸡血藤﹑浮萍﹑红花。包衣辅料为滑石粉。",
                "ggxh": "200丸",
                "pzwh": "国药准字Z11020834",
                "zzjb": "遗传性硬化性皮肤异色症,遗传性硬化性皮肤异色病,小儿风疹,雀斑,痤疮,湿疹,风疹,先天性风疹综合征,巴西紫热,脸上长斑",
                "zxbz": "",
                "manu": "北京同仁堂制药有限公司",
                "jj": "孕妇禁服。",
                "yxq": "36个月",
                "drugName": "皮肤病血毒丸",
                "ywxhzy": "如与其他药物同时使用可能会发生药物相互作用，详情请咨询医师或药师。",
                "xz": "本品为薄膜包衣的水丸，除去包衣后显黑褐色；味微苦。",
                "price": "12.00",
                "yfyl": "口服。一次20粒，一日2次。",
                "zc": "密封，干燥处保存。",
                "blfy": "",
                "type": "感染性疾病",
                "postage":"免邮费",
                "stock":13
            },
            {
                "syz": "本品用于促进创伤愈合作用。用于治疗外伤、手术创伤、烧伤、疤痕疙瘩及硬皮病。",
                "zysx": "孕妇慎用。过敏体质者慎用。",
                "id": "5b5f336dca3e848a6b0a2c10",
                "imgUrl": "https://image.360lj.com/s/upload/prodimage/201610/20161031103937135!320x320.jpg",
                "gnzz": "本品用于促进创伤愈合作用。用于治疗外伤、手术创伤、烧伤、疤痕疙瘩及硬皮病。",
                "zycf": "积雪草总苷",
                "ggxh": "每粒装0.15g（含积雪草总苷6mg）",
                "yfyl": "口服，一次2粒,一日3次；用于治疗疤痕疙瘩及硬皮病,一次2～4粒，一日3次。",
                "blfy": "尚不明确。",
                "zc": "密封，置阴凉处。",
                "tymc": "积雪苷胶囊",
                "manu": "广西古方药业有限公司",
                "spmc": "",
                "jj": "对本品过敏者禁用。",
                "yxq": "18个月",
                "drugName": "积雪苷胶囊",
                "zzjb": "外伤,手术创伤,烧伤,疤痕疙瘩,硬皮病",
                "zxbz": "",
                "ywxhzy": "未进行该项研究且暂无可靠文献参考。",
                "xz": "",
                "price": "36.00",
                "xgjb": "外伤 ,手术创伤 ,烧伤 ,疤痕疙瘩 ,硬皮病",
                "pzwh": "国药准字Z20090289",
                "tag": "",
                "type": "",
                "postage":"20元包邮",
                "stock":25
            }
        ]
    }
]